python_challenge/__init__.py
python_challenge-0.2.dist-info/LICENSE.txt
python_challenge-0.2.dist-info/METADATA
python_challenge-0.2.dist-info/WHEEL
python_challenge-0.2.dist-info/top_level.txt
python_challenge-0.2.dist-info/RECORD
