Metadata-Version: 2.1
Name: python-challenge
Version: 0.2
Summary: Python module to find value in a binary tree
Home-page: http://github.com/damolaajayi/python_challenge
Author: Adedamola Ajayi
Author-email: damolaajayi@gmail.com
License: MIT
Platform: UNKNOWN
